odp/__init__.py
odp/auth/__init__.py
odp/auth/cdf/__init__.py
odp/auth/cdf/cdf_token_handler.py
odp/auth/cdf/federated_cognite_client.py
odp/auth/odp/__init__.py
odp/auth/odp/interactive_login_token_handler.py
odp/auth/odp/ropc_token_handler.py
odp/auth/odp/token_handler.py
odp/auth/prefect/__init__.py
odp/auth/prefect/prefect_b2c_client.py
odp/client/__init__.py
odp/client/client.py
odp/client/credentials.py
odp/compute/__init__.py
odp/compute/blocks/__init__.py
odp/compute/blocks/aad_client_credentials.py
odp/compute/blocks/azure_key_vault.py
odp/compute/blocks/azure_storage.py
odp/compute/blocks/cdf_storage.py
odp/compute/blocks/db_engine.py
odp/compute/blocks/odcat.py
odp/compute/blocks/postgres.py
odp/compute/cli/__init__.py
odp/compute/cli/__main__.py
odp/compute/cli/authenticate.py
odp/compute/cli/block.py
odp/compute/cli/context.py
odp/compute/cli/deploy.py
odp/compute/cli/parameters.py
odp/compute/cli/params/__init__.py
odp/compute/cli/params/type_param_type.py
odp/compute/cli/run.py
odp/compute/cli/schema.py
odp/compute/config/__init__.py
odp/compute/config/cdf_config.py
odp/compute/config/dask_config.py
odp/compute/deploy/__init__.py
odp/compute/deploy/abstract_deployment_block.py
odp/compute/deploy/block/__init__.py
odp/compute/deploy/block/generic_block.py
odp/compute/deploy/deployment_block_factory.py
odp/compute/deploy/runtime/__init__.py
odp/compute/deploy/runtime/abstract_runtime.py
odp/compute/deploy/runtime/kubernetes.py
odp/compute/deploy/runtime/kubernetes_dask.py
odp/compute/deploy/runtime/kubernetes_tiered_resource.py
odp/compute/deploy/schedule/__init__.py
odp/compute/deploy/schedule/abstract_schedule.py
odp/compute/deploy/schedule/cron_schedule.py
odp/compute/deploy/schedule/interval_schedule.py
odp/compute/deploy/storage/__init__.py
odp/compute/deploy/storage/abstract_storage.py
odp/compute/deploy/storage/docker.py
odp/compute/deploy/storage/prefect_healthcheck.py
odp/compute/flow_state/__init__.py
odp_sdk_python_ingest-0.4.36.dist-info/METADATA
odp_sdk_python_ingest-0.4.36.dist-info/WHEEL
odp_sdk_python_ingest-0.4.36.dist-info/RECORD
